Snake/Food.py
Snake/__init__.py
Snake/main.py
Snake/scoreboard.py
Snake/snake.py
Snake_enzoscalassara-0.0.1.dist-info/LICENSE.txt
Snake_enzoscalassara-0.0.1.dist-info/METADATA
Snake_enzoscalassara-0.0.1.dist-info/WHEEL
Snake_enzoscalassara-0.0.1.dist-info/top_level.txt
Snake_enzoscalassara-0.0.1.dist-info/RECORD
