Metadata-Version: 2.1
Name: Snake-enzoscalassara
Version: 0.0.1
Summary: Snake I did
Home-page: https://github.com/enzoscalassara/package-test
Author: Enzo Scalassara
Author-email: enzo_scalassara@hotmail.com
License: UNKNOWN
Platform: UNKNOWN
Requires-Python: >=3.7
License-File: LICENSE.txt
